{
  "rows": [
    {
      "id_turma": 842093,
      "codigo_turma": "A",
      "ano": 2015,
      "periodo": 1,
      "id_curso_responsavel_oferta": null,
      "id_componente_curricular": 187899,
      "codigo_componente_curricular": "EMC0102",
      "nome_componente_curricular": "Introdução À Engenharia Mecânica",
      "nivel": "G",
      "tipo": 1,
      "tipo_turma": "Regular",
      "situacao_turma": "Consolidada",
      "horario": "4t56",
      "local": "Centro De Aulas D",
      "capacidade_aluno": 50,
      "total_matriculados": 45,
      "qtd_docentes": 1,
      "docentes": "[{\"Id_docente\" : 22657, \"Nome_docente\" : \"Felipe Pamplona Mariano\", \"Ch_teorica\" : 32, \"Ch_pratica\" : 0}]"
    },
    {
      "id_turma": 842094,
      "codigo_turma": "A",
      "ano": 2015,
      "periodo": 1,
      "id_curso_responsavel_oferta": null,
      "id_componente_curricular": 182771,
      "codigo_componente_curricular": "EMA0210",
      "nome_componente_curricular": "Conjunto Musical 1",
      "nivel": "G",
      "tipo": 1,
      "tipo_turma": "Regular",
      "situacao_turma": "Consolidada",
      "horario": "35m56",
      "local": "Sala 215",
      "capacidade_aluno": 100,
      "total_matriculados": 31,
      "qtd_docentes": 2,
      "docentes": "[{\"Id_docente\" : 23698, \"Nome_docente\" : \"Carlos Henrique Coutinho Rodrigues Costa\", \"Ch_teorica\" : 0, \"Ch_pratica\" : 16}, {\"Id_docente\" : 28131, \"Nome_docente\" : \"Weber Barbosa De Assis\", \"Ch_teorica\" : 0, \"Ch_pratica\" : 16}]"
    },
    {
      "id_turma": 842095,
      "codigo_turma": "B",
      "ano": 2015,
      "periodo": 1,
      "id_curso_responsavel_oferta": null,
      "id_componente_curricular": 181162,
      "codigo_componente_curricular": "EMC0006",
      "nome_componente_curricular": "Análise De Sistemas Lineares",
      "nivel": "G",
      "tipo": 1,
      "tipo_turma": "Regular",
      "situacao_turma": "Consolidada",
      "horario": "36m34",
      "local": "Emc",
      "capacidade_aluno": 40,
      "total_matriculados": 11,
      "qtd_docentes": 1,
      "docentes": "[{\"Id_docente\" : 21946, \"Nome_docente\" : \"Sergio Pires Pimentel\", \"Ch_teorica\" : 64, \"Ch_pratica\" : 0}]"
    },
    {
      "id_turma": 842096,
      "codigo_turma": "A",
      "ano": 2015,
      "periodo": 1,
      "id_curso_responsavel_oferta": null,
      "id_componente_curricular": 189426,
      "codigo_componente_curricular": "EMC0157",
      "nome_componente_curricular": "Metodologia Científica",
      "nivel": "G",
      "tipo": 1,
      "tipo_turma": "Regular",
      "situacao_turma": "Consolidada",
      "horario": "6m12",
      "local": "Emc",
      "capacidade_aluno": 41,
      "total_matriculados": 41,
      "qtd_docentes": 1,
      "docentes": "[{\"Id_docente\" : 16222, \"Nome_docente\" : \"Weber Martins\", \"Ch_teorica\" : 32, \"Ch_pratica\" : 0}]"
    },
    {
      "id_turma": 842097,
      "codigo_turma": "A",
      "ano": 2015,
      "periodo": 1,
      "id_curso_responsavel_oferta": null,
      "id_componente_curricular": 188472,
      "codigo_componente_curricular": "EMC0140",
      "nome_componente_curricular": "Laboratório De Sistemas De Controle",
      "nivel": "G",
      "tipo": 1,
      "tipo_turma": "Regular",
      "situacao_turma": "Consolidada",
      "horario": "2m56",
      "local": "Emc",
      "capacidade_aluno": 9,
      "total_matriculados": 7,
      "qtd_docentes": 1,
      "docentes": "[{\"Id_docente\" : 24670, \"Nome_docente\" : \"Gisele Guimaraes\", \"Ch_teorica\" : 0, \"Ch_pratica\" : 32}]"
    },
    {
      "id_turma": 842099,
      "codigo_turma": "A",
      "ano": 2015,
      "periodo": 1,
      "id_curso_responsavel_oferta": null,
      "id_componente_curricular": 184091,
      "codigo_componente_curricular": "EMC0048",
      "nome_componente_curricular": "Elementos De Máquinas 2",
      "nivel": "G",
      "tipo": 1,
      "tipo_turma": "Regular",
      "situacao_turma": "Consolidada",
      "horario": "35v12",
      "local": "Sala 11 - Bloco B - Emc",
      "capacidade_aluno": 40,
      "total_matriculados": 26,
      "qtd_docentes": 1,
      "docentes": "[{\"Id_docente\" : 27021, \"Nome_docente\" : \"Marlipe Garcia Fagundes Neto\", \"Ch_teorica\" : 64, \"Ch_pratica\" : 0}]"
    },
    {
      "id_turma": 842100,
      "codigo_turma": "A",
      "ano": 2015,
      "periodo": 1,
      "id_curso_responsavel_oferta": null,
      "id_componente_curricular": 189133,
      "codigo_componente_curricular": "EMC0143",
      "nome_componente_curricular": "Manutenção Industrial",
      "nivel": "G",
      "tipo": 1,
      "tipo_turma": "Regular",
      "situacao_turma": "Consolidada",
      "horario": "24m56",
      "local": "Sala 11 - Bloco B - Emc",
      "capacidade_aluno": 40,
      "total_matriculados": 16,
      "qtd_docentes": 1,
      "docentes": "[{\"Id_docente\" : 20234, \"Nome_docente\" : \"Kleber Mendes De Figueiredo\", \"Ch_teorica\" : 32, \"Ch_pratica\" : 32}]"
    },
    {
      "id_turma": 842101,
      "codigo_turma": "A",
      "ano": 2015,
      "periodo": 1,
      "id_curso_responsavel_oferta": null,
      "id_componente_curricular": 184231,
      "codigo_componente_curricular": "EMC0070",
      "nome_componente_curricular": "Engenharia De Segurança",
      "nivel": "G",
      "tipo": 1,
      "tipo_turma": "Regular",
      "situacao_turma": "Consolidada",
      "horario": "5m34",
      "local": "Sala 11 - Bloco B - Emc",
      "capacidade_aluno": 42,
      "total_matriculados": 50,
      "qtd_docentes": 1,
      "docentes": "[{\"Id_docente\" : 20471, \"Nome_docente\" : \"Cacilda De Jesus Ribeiro\", \"Ch_teorica\" : 32, \"Ch_pratica\" : 0}]"
    },
    {
      "id_turma": 842103,
      "codigo_turma": "A",
      "ano": 2015,
      "periodo": 1,
      "id_curso_responsavel_oferta": null,
      "id_componente_curricular": 182909,
      "codigo_componente_curricular": "EMC0032",
      "nome_componente_curricular": "Controle De Qualidade",
      "nivel": "G",
      "tipo": 1,
      "tipo_turma": "Regular",
      "situacao_turma": "Consolidada",
      "horario": "24v34",
      "local": "Emc",
      "capacidade_aluno": 40,
      "total_matriculados": 38,
      "qtd_docentes": 1,
      "docentes": "[{\"Id_docente\" : 20234, \"Nome_docente\" : \"Kleber Mendes De Figueiredo\", \"Ch_teorica\" : 64, \"Ch_pratica\" : 0}]"
    },
    {
      "id_turma": 842104,
      "codigo_turma": "A",
      "ano": 2015,
      "periodo": 1,
      "id_curso_responsavel_oferta": null,
      "id_componente_curricular": 194219,
      "codigo_componente_curricular": "EMC0222",
      "nome_componente_curricular": "Tecnologia Da Soldagem",
      "nivel": "G",
      "tipo": 1,
      "tipo_turma": "Regular",
      "situacao_turma": "Consolidada",
      "horario": "35m12",
      "local": "Emc",
      "capacidade_aluno": 40,
      "total_matriculados": 26,
      "qtd_docentes": 1,
      "docentes": "[{\"Id_docente\" : 21578, \"Nome_docente\" : \"Demostenes Ferreira Filho\", \"Ch_teorica\" : 64, \"Ch_pratica\" : 0}]"
    },
    {
      "id_turma": 842105,
      "codigo_turma": "A",
      "ano": 2015,
      "periodo": 1,
      "id_curso_responsavel_oferta": null,
      "id_componente_curricular": 181756,
      "codigo_componente_curricular": "EEC0018",
      "nome_componente_curricular": "Avaliação De Impactos E Riscos Amb: Estudo De Caso",
      "nivel": "G",
      "tipo": 1,
      "tipo_turma": "Regular",
      "situacao_turma": "Consolidada",
      "horario": "2v1234",
      "local": "Sala 210 Centro De Aulas D",
      "capacidade_aluno": 50,
      "total_matriculados": 8,
      "qtd_docentes": 1,
      "docentes": "[{\"Id_docente\" : 23029, \"Nome_docente\" : \"Denilson Teixeira\", \"Ch_teorica\" : 48, \"Ch_pratica\" : 16}]"
    },
    {
      "id_turma": 842106,
      "codigo_turma": "A",
      "ano": 2015,
      "periodo": 1,
      "id_curso_responsavel_oferta": null,
      "id_componente_curricular": 181825,
      "codigo_componente_curricular": "EEC0021",
      "nome_componente_curricular": "Biodiversidade E Unidades De Conservação",
      "nivel": "G",
      "tipo": 1,
      "tipo_turma": "Regular",
      "situacao_turma": "Consolidada",
      "horario": "4v45 5v56  5n1",
      "local": "Sala 2 Eec",
      "capacidade_aluno": 50,
      "total_matriculados": 50,
      "qtd_docentes": 1,
      "docentes": "[{\"Id_docente\" : 23945, \"Nome_docente\" : \"Katia Alcione Kopp\", \"Ch_teorica\" : 48, \"Ch_pratica\" : 16}]"
    },
    {
      "id_turma": 842108,
      "codigo_turma": "A",
      "ano": 2015,
      "periodo": 1,
      "id_curso_responsavel_oferta": null,
      "id_componente_curricular": 195226,
      "codigo_componente_curricular": "EEC0285",
      "nome_componente_curricular": "Tratamento De Água De Abastecimento",
      "nivel": "G",
      "tipo": 1,
      "tipo_turma": "Regular",
      "situacao_turma": "Consolidada",
      "horario": "4m1234",
      "local": "Sala 2 Bloco B Da Eec",
      "capacidade_aluno": 45,
      "total_matriculados": 26,
      "qtd_docentes": 1,
      "docentes": "[{\"Id_docente\" : 18765, \"Nome_docente\" : \"Paulo Sergio Scalize\", \"Ch_teorica\" : 48, \"Ch_pratica\" : 16}]"
    },
    {
      "id_turma": 842109,
      "codigo_turma": "A",
      "ano": 2015,
      "periodo": 1,
      "id_curso_responsavel_oferta": null,
      "id_componente_curricular": 195160,
      "codigo_componente_curricular": "EEC0278",
      "nome_componente_curricular": "Trabalho De Conclusão De Curso 2",
      "nivel": "G",
      "tipo": 1,
      "tipo_turma": "Regular",
      "situacao_turma": "Consolidada",
      "horario": "3t5",
      "local": "Eec",
      "capacidade_aluno": 40,
      "total_matriculados": 15,
      "qtd_docentes": 1,
      "docentes": "[{\"Id_docente\" : 23945, \"Nome_docente\" : \"Katia Alcione Kopp\", \"Ch_teorica\" : 0, \"Ch_pratica\" : 16}]"
    },
    {
      "id_turma": 842113,
      "codigo_turma": "A",
      "ano": 2015,
      "periodo": 1,
      "id_curso_responsavel_oferta": null,
      "id_componente_curricular": 193556,
      "codigo_componente_curricular": "EEC0223",
      "nome_componente_curricular": "Resistência Dos Materiais",
      "nivel": "G",
      "tipo": 1,
      "tipo_turma": "Regular",
      "situacao_turma": "Consolidada",
      "horario": "36m12",
      "local": "Sala 405 Do Centro De Aulas \"D\"",
      "capacidade_aluno": 62,
      "total_matriculados": 84,
      "qtd_docentes": 1,
      "docentes": "[{\"Id_docente\" : 27209, \"Nome_docente\" : \"Janes Cleiton Alves De Oliveira\", \"Ch_teorica\" : 64, \"Ch_pratica\" : 0}]"
    },
    {
      "id_turma": 842116,
      "codigo_turma": "A",
      "ano": 2015,
      "periodo": 1,
      "id_curso_responsavel_oferta": null,
      "id_componente_curricular": 191231,
      "codigo_componente_curricular": "EEC0198",
      "nome_componente_curricular": "Planejamento Urbano E Ambiental",
      "nivel": "G",
      "tipo": 1,
      "tipo_turma": "Regular",
      "situacao_turma": "Consolidada",
      "horario": "6m1234",
      "local": "Eec",
      "capacidade_aluno": 50,
      "total_matriculados": 23,
      "qtd_docentes": 1,
      "docentes": "[{\"Id_docente\" : 22444, \"Nome_docente\" : \"Karla Emmanuela Ribeiro Hora\", \"Ch_teorica\" : 48, \"Ch_pratica\" : 16}]"
    },
    {
      "id_turma": 842122,
      "codigo_turma": "A",
      "ano": 2015,
      "periodo": 1,
      "id_curso_responsavel_oferta": null,
      "id_componente_curricular": 187933,
      "codigo_componente_curricular": "EEC0140",
      "nome_componente_curricular": "Introdução À Geotecnia",
      "nivel": "G",
      "tipo": 1,
      "tipo_turma": "Regular",
      "situacao_turma": "Consolidada",
      "horario": "2t6  2n1",
      "local": "Centro De Aulas D 106",
      "capacidade_aluno": 50,
      "total_matriculados": 58,
      "qtd_docentes": 1,
      "docentes": "[{\"Id_docente\" : 20110, \"Nome_docente\" : \"Carlos Alberto Lauro Vargas\", \"Ch_teorica\" : 32, \"Ch_pratica\" : 0}]"
    },
    {
      "id_turma": 842123,
      "codigo_turma": "A",
      "ano": 2015,
      "periodo": 1,
      "id_curso_responsavel_oferta": null,
      "id_componente_curricular": 187887,
      "codigo_componente_curricular": "EEC0138",
      "nome_componente_curricular": "Introdução À Engenharia Ambiental E Sanitária",
      "nivel": "G",
      "tipo": 1,
      "tipo_turma": "Regular",
      "situacao_turma": "Consolidada",
      "horario": "4t12",
      "local": "Sala 6 Da Eec",
      "capacidade_aluno": 50,
      "total_matriculados": 58,
      "qtd_docentes": 1,
      "docentes": "[{\"Id_docente\" : 18765, \"Nome_docente\" : \"Paulo Sergio Scalize\", \"Ch_teorica\" : 16, \"Ch_pratica\" : 16}]"
    },
    {
      "id_turma": 842124,
      "codigo_turma": "A",
      "ano": 2015,
      "periodo": 1,
      "id_curso_responsavel_oferta": null,
      "id_componente_curricular": 186607,
      "codigo_componente_curricular": "EEC0114",
      "nome_componente_curricular": "Gerenciamento De Resíduos Sólidos E Urbanos",
      "nivel": "G",
      "tipo": 1,
      "tipo_turma": "Regular",
      "situacao_turma": "Consolidada",
      "horario": "3t1234",
      "local": "Sala 2",
      "capacidade_aluno": 50,
      "total_matriculados": 47,
      "qtd_docentes": 1,
      "docentes": "[{\"Id_docente\" : 21743, \"Nome_docente\" : \"Simone Costa Pfeiffer\", \"Ch_teorica\" : 48, \"Ch_pratica\" : 16}]"
    },
    {
      "id_turma": 842125,
      "codigo_turma": "A",
      "ano": 2015,
      "periodo": 1,
      "id_curso_responsavel_oferta": null,
      "id_componente_curricular": 189285,
      "codigo_componente_curricular": "EEC0170",
      "nome_componente_curricular": "Mecânica Dos Solos Ii",
      "nivel": "G",
      "tipo": 1,
      "tipo_turma": "Regular",
      "situacao_turma": "Consolidada",
      "horario": "3t56 5t12",
      "local": "Eec",
      "capacidade_aluno": 50,
      "total_matriculados": 50,
      "qtd_docentes": 1,
      "docentes": "[{\"Id_docente\" : 21903, \"Nome_docente\" : \"Marcia Maria Dos Anjos Mascarenha\", \"Ch_teorica\" : 64, \"Ch_pratica\" : 0}]"
    },
    {
      "id_turma": 842127,
      "codigo_turma": "A",
      "ano": 2015,
      "periodo": 1,
      "id_curso_responsavel_oferta": null,
      "id_componente_curricular": 186815,
      "codigo_componente_curricular": "EEC0129",
      "nome_componente_curricular": "Hidrologia",
      "nivel": "G",
      "tipo": 1,
      "tipo_turma": "Regular",
      "situacao_turma": "Consolidada",
      "horario": "4t6 5t34  4n1",
      "local": "Eec",
      "capacidade_aluno": 50,
      "total_matriculados": 47,
      "qtd_docentes": 1,
      "docentes": "[{\"Id_docente\" : 20088, \"Nome_docente\" : \"Klebber Teodomiro Martins Formiga\", \"Ch_teorica\" : 48, \"Ch_pratica\" : 16}]"
    },
    {
      "id_turma": 842128,
      "codigo_turma": "A",
      "ano": 2015,
      "periodo": 1,
      "id_curso_responsavel_oferta": null,
      "id_componente_curricular": 182798,
      "codigo_componente_curricular": "EEC0041",
      "nome_componente_curricular": "Construção Civil",
      "nivel": "G",
      "tipo": 1,
      "tipo_turma": "Regular",
      "situacao_turma": "Consolidada",
      "horario": "2m34",
      "local": "Sala 02 Eec",
      "capacidade_aluno": 51,
      "total_matriculados": 53,
      "qtd_docentes": 1,
      "docentes": "[{\"Id_docente\" : 21362, \"Nome_docente\" : \"Maria Carolina Gomes De Oliveira Brandstetter\", \"Ch_teorica\" : 32, \"Ch_pratica\" : 0}]"
    },
    {
      "id_turma": 842129,
      "codigo_turma": "A",
      "ano": 2015,
      "periodo": 1,
      "id_curso_responsavel_oferta": null,
      "id_componente_curricular": 183919,
      "codigo_componente_curricular": "EEC0063",
      "nome_componente_curricular": "Educação Ambiental",
      "nivel": "G",
      "tipo": 1,
      "tipo_turma": "Regular",
      "situacao_turma": "Consolidada",
      "horario": "2m56",
      "local": "Sala 2 Da Eec",
      "capacidade_aluno": 54,
      "total_matriculados": 54,
      "qtd_docentes": 1,
      "docentes": "[{\"Id_docente\" : 23945, \"Nome_docente\" : \"Katia Alcione Kopp\", \"Ch_teorica\" : 32, \"Ch_pratica\" : 0}]"
    },
    {
      "id_turma": 842130,
      "codigo_turma": "A",
      "ano": 2015,
      "periodo": 1,
      "id_curso_responsavel_oferta": null,
      "id_componente_curricular": 182471,
      "codigo_componente_curricular": "EEC0030",
      "nome_componente_curricular": "Coleta E Transporte De Esgoto Sanitário",
      "nivel": "G",
      "tipo": 1,
      "tipo_turma": "Regular",
      "situacao_turma": "Consolidada",
      "horario": "2t1234",
      "local": "Sala 1 Bloco B Da Eec",
      "capacidade_aluno": 30,
      "total_matriculados": 21,
      "qtd_docentes": 1,
      "docentes": "[{\"Id_docente\" : 19174, \"Nome_docente\" : \"Eraldo Henriques De Carvalho\", \"Ch_teorica\" : 48, \"Ch_pratica\" : 16}]"
    },
    {
      "id_turma": 842131,
      "codigo_turma": "B",
      "ano": 2015,
      "periodo": 1,
      "id_curso_responsavel_oferta": null,
      "id_componente_curricular": 182471,
      "codigo_componente_curricular": "EEC0030",
      "nome_componente_curricular": "Coleta E Transporte De Esgoto Sanitário",
      "nivel": "G",
      "tipo": 1,
      "tipo_turma": "Regular",
      "situacao_turma": "Consolidada",
      "horario": "3m3456",
      "local": "Sala 2 Da Eec",
      "capacidade_aluno": 30,
      "total_matriculados": 18,
      "qtd_docentes": 1,
      "docentes": "[{\"Id_docente\" : 22941, \"Nome_docente\" : \"Francisco Javier Cuba Teran\", \"Ch_teorica\" : 48, \"Ch_pratica\" : 16}]"
    },
    {
      "id_turma": 842132,
      "codigo_turma": "A",
      "ano": 2015,
      "periodo": 1,
      "id_curso_responsavel_oferta": null,
      "id_componente_curricular": 186812,
      "codigo_componente_curricular": "EEC0127",
      "nome_componente_curricular": "Hidrogeologia",
      "nivel": "G",
      "tipo": 1,
      "tipo_turma": "Regular",
      "situacao_turma": "Consolidada",
      "horario": "35m12",
      "local": "Sala 2 Da Eec",
      "capacidade_aluno": 45,
      "total_matriculados": 29,
      "qtd_docentes": 1,
      "docentes": "[{\"Id_docente\" : 15875, \"Nome_docente\" : \"Jose Vicente Granato De Araujo\", \"Ch_teorica\" : 48, \"Ch_pratica\" : 16}]"
    },
    {
      "id_turma": 842133,
      "codigo_turma": "A",
      "ano": 2015,
      "periodo": 1,
      "id_curso_responsavel_oferta": null,
      "id_componente_curricular": 189722,
      "codigo_componente_curricular": "EEC0178",
      "nome_componente_curricular": "Modelagem De Sistemas Ambientais",
      "nivel": "G",
      "tipo": 1,
      "tipo_turma": "Regular",
      "situacao_turma": "Consolidada",
      "horario": "3t6 5t56  3n1",
      "local": "Sala 01 Nas Terças E Sala 3 Nas Quintas",
      "capacidade_aluno": 50,
      "total_matriculados": 19,
      "qtd_docentes": 1,
      "docentes": "[{\"Id_docente\" : 18826, \"Nome_docente\" : \"Eduardo Queija De Siqueira\", \"Ch_teorica\" : 48, \"Ch_pratica\" : 16}]"
    },
    {
      "id_turma": 842134,
      "codigo_turma": "A",
      "ano": 2015,
      "periodo": 1,
      "id_curso_responsavel_oferta": null,
      "id_componente_curricular": 188220,
      "codigo_componente_curricular": "EEC0148",
      "nome_componente_curricular": "Irrigação E Drenagem",
      "nivel": "G",
      "tipo": 1,
      "tipo_turma": "Regular",
      "situacao_turma": "Consolidada",
      "horario": "4t34 6t12",
      "local": "Eec",
      "capacidade_aluno": 45,
      "total_matriculados": 22,
      "qtd_docentes": 1,
      "docentes": "[{\"Id_docente\" : 21811, \"Nome_docente\" : \"Saulo Bruno Silveira E Souza\", \"Ch_teorica\" : 48, \"Ch_pratica\" : 16}]"
    },
    {
      "id_turma": 842135,
      "codigo_turma": "A",
      "ano": 2015,
      "periodo": 1,
      "id_curso_responsavel_oferta": null,
      "id_componente_curricular": 186608,
      "codigo_componente_curricular": "EEC0115",
      "nome_componente_curricular": "Gerenciamento De Resíduos Sólidos Industriais",
      "nivel": "G",
      "tipo": 1,
      "tipo_turma": "Regular",
      "situacao_turma": "Consolidada",
      "horario": "5m345",
      "local": "Sala 2 Da Eec, Bloco \"B\"",
      "capacidade_aluno": 50,
      "total_matriculados": 30,
      "qtd_docentes": 1,
      "docentes": "[{\"Id_docente\" : 21743, \"Nome_docente\" : \"Simone Costa Pfeiffer\", \"Ch_teorica\" : 32, \"Ch_pratica\" : 16}]"
    },
    {
      "id_turma": 842138,
      "codigo_turma": "A",
      "ano": 2015,
      "periodo": 1,
      "id_curso_responsavel_oferta": null,
      "id_componente_curricular": 195223,
      "codigo_componente_curricular": "EEC0283",
      "nome_componente_curricular": "Tratamento Avançado De Água De Abastecimento",
      "nivel": "G",
      "tipo": 1,
      "tipo_turma": "Regular",
      "situacao_turma": "Consolidada",
      "horario": "4t456",
      "local": "Eec",
      "capacidade_aluno": 50,
      "total_matriculados": 13,
      "qtd_docentes": 1,
      "docentes": "[{\"Id_docente\" : 27450, \"Nome_docente\" : \"Humberto Carlos Ruggeri Junior\", \"Ch_teorica\" : 32, \"Ch_pratica\" : 16}]"
    },
    {
      "id_turma": 842139,
      "codigo_turma": "A",
      "ano": 2015,
      "periodo": 1,
      "id_curso_responsavel_oferta": null,
      "id_componente_curricular": 185133,
      "codigo_componente_curricular": "EEC0091",
      "nome_componente_curricular": "Estruturas De Contenções E Estabilidade De Taludes",
      "nivel": "G",
      "tipo": 1,
      "tipo_turma": "Regular",
      "situacao_turma": "Consolidada",
      "horario": "35m56",
      "local": "Sala 3 Bloco B Eec",
      "capacidade_aluno": 30,
      "total_matriculados": 22,
      "qtd_docentes": 1,
      "docentes": "[{\"Id_docente\" : 20110, \"Nome_docente\" : \"Carlos Alberto Lauro Vargas\", \"Ch_teorica\" : 64, \"Ch_pratica\" : 0}]"
    },
    {
      "id_turma": 842140,
      "codigo_turma": "A",
      "ano": 2015,
      "periodo": 1,
      "id_curso_responsavel_oferta": null,
      "id_componente_curricular": 188688,
      "codigo_componente_curricular": "EEC0154",
      "nome_componente_curricular": "Licenciamento Ambiental",
      "nivel": "G",
      "tipo": 1,
      "tipo_turma": "Regular",
      "situacao_turma": "Consolidada",
      "horario": "5v1234",
      "local": "Eec",
      "capacidade_aluno": 45,
      "total_matriculados": 19,
      "qtd_docentes": 1,
      "docentes": "[{\"Id_docente\" : 23019, \"Nome_docente\" : \"Emiliano Lobo De Godoi\", \"Ch_teorica\" : 48, \"Ch_pratica\" : 16}]"
    },
    {
      "id_turma": 842141,
      "codigo_turma": "A",
      "ano": 2015,
      "periodo": 1,
      "id_curso_responsavel_oferta": null,
      "id_componente_curricular": 191202,
      "codigo_componente_curricular": "EEC0195",
      "nome_componente_curricular": "Planejamento E Gestão Ambiental",
      "nivel": "G",
      "tipo": 1,
      "tipo_turma": "Regular",
      "situacao_turma": "Consolidada",
      "horario": "5t56  5n1",
      "local": "Eec",
      "capacidade_aluno": 50,
      "total_matriculados": 13,
      "qtd_docentes": 1,
      "docentes": "[{\"Id_docente\" : 23019, \"Nome_docente\" : \"Emiliano Lobo De Godoi\", \"Ch_teorica\" : 48, \"Ch_pratica\" : 0}]"
    },
    {
      "id_turma": 842142,
      "codigo_turma": "A",
      "ano": 2015,
      "periodo": 1,
      "id_curso_responsavel_oferta": null,
      "id_componente_curricular": 190382,
      "codigo_componente_curricular": "EEC0182",
      "nome_componente_curricular": "Obras E Serviços De Saneamento",
      "nivel": "G",
      "tipo": 1,
      "tipo_turma": "Regular",
      "situacao_turma": "Consolidada",
      "horario": "6t345",
      "local": "Sala 2 Da Eec",
      "capacidade_aluno": 45,
      "total_matriculados": 36,
      "qtd_docentes": 1,
      "docentes": "[{\"Id_docente\" : 27450, \"Nome_docente\" : \"Humberto Carlos Ruggeri Junior\", \"Ch_teorica\" : 40, \"Ch_pratica\" : 8}]"
    },
    {
      "id_turma": 842144,
      "codigo_turma": "A",
      "ano": 2015,
      "periodo": 1,
      "id_curso_responsavel_oferta": null,
      "id_componente_curricular": 189759,
      "codigo_componente_curricular": "EEC0180",
      "nome_componente_curricular": "Monitoramento Ambiental",
      "nivel": "G",
      "tipo": 1,
      "tipo_turma": "Regular",
      "situacao_turma": "Consolidada",
      "horario": "3v1234",
      "local": "Eec",
      "capacidade_aluno": 50,
      "total_matriculados": 34,
      "qtd_docentes": 1,
      "docentes": "[{\"Id_docente\" : 18965, \"Nome_docente\" : \"Nilson Clementino Ferreira\", \"Ch_teorica\" : 48, \"Ch_pratica\" : 16}]"
    },
    {
      "id_turma": 842145,
      "codigo_turma": "A",
      "ano": 2015,
      "periodo": 1,
      "id_curso_responsavel_oferta": null,
      "id_componente_curricular": 188424,
      "codigo_componente_curricular": "EEC0153",
      "nome_componente_curricular": "Laboratório De Mecânica Dos Solos Ii",
      "nivel": "G",
      "tipo": 1,
      "tipo_turma": "Regular",
      "situacao_turma": "Consolidada",
      "horario": "6v2",
      "local": "Eec",
      "capacidade_aluno": 25,
      "total_matriculados": 30,
      "qtd_docentes": 1,
      "docentes": "[{\"Id_docente\" : 23221, \"Nome_docente\" : \"Renato Resende Angelim\", \"Ch_teorica\" : 0, \"Ch_pratica\" : 16}]"
    },
    {
      "id_turma": 842146,
      "codigo_turma": "B",
      "ano": 2015,
      "periodo": 1,
      "id_curso_responsavel_oferta": null,
      "id_componente_curricular": 188424,
      "codigo_componente_curricular": "EEC0153",
      "nome_componente_curricular": "Laboratório De Mecânica Dos Solos Ii",
      "nivel": "G",
      "tipo": 1,
      "tipo_turma": "Regular",
      "situacao_turma": "Consolidada",
      "horario": "6t3",
      "local": "Eec",
      "capacidade_aluno": 25,
      "total_matriculados": 20,
      "qtd_docentes": 1,
      "docentes": "[{\"Id_docente\" : 23221, \"Nome_docente\" : \"Renato Resende Angelim\", \"Ch_teorica\" : 0, \"Ch_pratica\" : 16}]"
    },
    {
      "id_turma": 842148,
      "codigo_turma": "C01",
      "ano": 2015,
      "periodo": 1,
      "id_curso_responsavel_oferta": null,
      "id_componente_curricular": 181977,
      "codigo_componente_curricular": "EEC0022",
      "nome_componente_curricular": "Biologia Geral",
      "nivel": "G",
      "tipo": 1,
      "tipo_turma": "Regular",
      "situacao_turma": "Consolidada",
      "horario": "2t123 4t3",
      "local": "Sala 110 Ca \"D\" E Lab Saneamento",
      "capacidade_aluno": 28,
      "total_matriculados": 35,
      "qtd_docentes": 1,
      "docentes": "[{\"Id_docente\" : 21938, \"Nome_docente\" : \"Nora Katia Saavedra Del Aguila Hoffmann\", \"Ch_teorica\" : 24, \"Ch_pratica\" : 16}]"
    },
    {
      "id_turma": 842153,
      "codigo_turma": "A",
      "ano": 2015,
      "periodo": 1,
      "id_curso_responsavel_oferta": null,
      "id_componente_curricular": 185433,
      "codigo_componente_curricular": "EEC0098",
      "nome_componente_curricular": "Fenômenos De Transporte I",
      "nivel": "G",
      "tipo": 1,
      "tipo_turma": "Regular",
      "situacao_turma": "Consolidada",
      "horario": "4m12 6m34",
      "local": "Salas Do Centros De Aulas \"D\": 104 (Quartas) 406 (Sextas)",
      "capacidade_aluno": 60,
      "total_matriculados": 67,
      "qtd_docentes": 1,
      "docentes": "[{\"Id_docente\" : 21811, \"Nome_docente\" : \"Saulo Bruno Silveira E Souza\", \"Ch_teorica\" : 48, \"Ch_pratica\" : 16}]"
    },
    {
      "id_turma": 842154,
      "codigo_turma": "A",
      "ano": 2015,
      "periodo": 1,
      "id_curso_responsavel_oferta": null,
      "id_componente_curricular": 195147,
      "codigo_componente_curricular": "EEC0275",
      "nome_componente_curricular": "Trabalho De Conclusão De Curso 1",
      "nivel": "G",
      "tipo": 1,
      "tipo_turma": "Regular",
      "situacao_turma": "Consolidada",
      "horario": "2t5",
      "local": "Sala 1",
      "capacidade_aluno": 50,
      "total_matriculados": 17,
      "qtd_docentes": 1,
      "docentes": "[{\"Id_docente\" : 23029, \"Nome_docente\" : \"Denilson Teixeira\", \"Ch_teorica\" : 0, \"Ch_pratica\" : 16}]"
    },
    {
      "id_turma": 842156,
      "codigo_turma": "A01",
      "ano": 2015,
      "periodo": 1,
      "id_curso_responsavel_oferta": null,
      "id_componente_curricular": 193165,
      "codigo_componente_curricular": "INQ0176",
      "nome_componente_curricular": "Química Orgânica Ii",
      "nivel": "G",
      "tipo": 1,
      "tipo_turma": "Regular",
      "situacao_turma": "Consolidada",
      "horario": "2m2345  4t45",
      "local": "Sala 2 Ff E Lpf 3",
      "capacidade_aluno": 15,
      "total_matriculados": 23,
      "qtd_docentes": 2,
      "docentes": "[{\"Id_docente\" : 20727, \"Nome_docente\" : \"Ricardo Menegatti\", \"Ch_teorica\" : 12, \"Ch_pratica\" : 16}, {\"Id_docente\" : 22323, \"Nome_docente\" : \"Pierre Alexandre Dos Santos\", \"Ch_teorica\" : 12, \"Ch_pratica\" : 16}]"
    },
    {
      "id_turma": 842158,
      "codigo_turma": "A",
      "ano": 2015,
      "periodo": 1,
      "id_curso_responsavel_oferta": null,
      "id_componente_curricular": 195224,
      "codigo_componente_curricular": "EEC0284",
      "nome_componente_curricular": "Tratamento Avançado De Esgoto Sanitário",
      "nivel": "G",
      "tipo": 1,
      "tipo_turma": "Regular",
      "situacao_turma": "Consolidada",
      "horario": "4t123",
      "local": "Eec",
      "capacidade_aluno": 45,
      "total_matriculados": 9,
      "qtd_docentes": 1,
      "docentes": "[{\"Id_docente\" : 22941, \"Nome_docente\" : \"Francisco Javier Cuba Teran\", \"Ch_teorica\" : 32, \"Ch_pratica\" : 16}]"
    },
    {
      "id_turma": 842162,
      "codigo_turma": "A",
      "ano": 2015,
      "periodo": 1,
      "id_curso_responsavel_oferta": null,
      "id_componente_curricular": 181848,
      "codigo_componente_curricular": "IPT0008",
      "nome_componente_curricular": "Bioética",
      "nivel": "G",
      "tipo": 1,
      "tipo_turma": "Regular",
      "situacao_turma": "Consolidada",
      "horario": "3m23 (23/02/2015 - 04/07/2015)",
      "local": "Ca-D",
      "capacidade_aluno": 32,
      "total_matriculados": 30,
      "qtd_docentes": 1,
      "docentes": "[{\"Id_docente\" : 18840, \"Nome_docente\" : \"Ana Maria De Oliveira\", \"Ch_teorica\" : 32, \"Ch_pratica\" : 0}]"
    },
    {
      "id_turma": 842163,
      "codigo_turma": "A01",
      "ano": 2015,
      "periodo": 1,
      "id_curso_responsavel_oferta": null,
      "id_componente_curricular": 183071,
      "codigo_componente_curricular": "IPT0021",
      "nome_componente_curricular": "Cultura De Célula Animal",
      "nivel": "G",
      "tipo": 1,
      "tipo_turma": "Regular",
      "situacao_turma": "Consolidada",
      "horario": "4t23 (23/02/2015 - 04/07/2015)",
      "local": "Ca-D",
      "capacidade_aluno": 16,
      "total_matriculados": 15,
      "qtd_docentes": 3,
      "docentes": "[{\"Id_docente\" : 23511, \"Nome_docente\" : \"Menira Borges De Lima Dias E Souza\", \"Ch_teorica\" : 2, \"Ch_pratica\" : 0}, {\"Id_docente\" : 24082, \"Nome_docente\" : \"Fabiola Souza Fiaccadori\", \"Ch_teorica\" : 2, \"Ch_pratica\" : 8}, {\"Id_docente\" : 18865, \"Nome_docente\" : \"Adriana De Moraes Costa Crespo\", \"Ch_teorica\" : 4, \"Ch_pratica\" : 8}]"
    },
    {
      "id_turma": 842165,
      "codigo_turma": "A",
      "ano": 2015,
      "periodo": 1,
      "id_curso_responsavel_oferta": null,
      "id_componente_curricular": 194614,
      "codigo_componente_curricular": "IPT0098",
      "nome_componente_curricular": "Tópicos Avançados Em Biotecnologia I",
      "nivel": "G",
      "tipo": 1,
      "tipo_turma": "Regular",
      "situacao_turma": "Consolidada",
      "horario": "3m23 (23/02/2015 - 04/07/2015)",
      "local": "Ca-D",
      "capacidade_aluno": 32,
      "total_matriculados": 21,
      "qtd_docentes": 1,
      "docentes": "[{\"Id_docente\" : 27340, \"Nome_docente\" : \"Pedro Vitor Lemos Cravo\", \"Ch_teorica\" : 32, \"Ch_pratica\" : 0}]"
    },
    {
      "id_turma": 842170,
      "codigo_turma": "A",
      "ano": 2015,
      "periodo": 1,
      "id_curso_responsavel_oferta": null,
      "id_componente_curricular": 193828,
      "codigo_componente_curricular": "IPT0096",
      "nome_componente_curricular": "Seminários Em Biotecnologia",
      "nivel": "G",
      "tipo": 1,
      "tipo_turma": "Regular",
      "situacao_turma": "Consolidada",
      "horario": "5t45 (23/02/2015 - 04/07/2015)",
      "local": "Ca-D",
      "capacidade_aluno": 32,
      "total_matriculados": 19,
      "qtd_docentes": 1,
      "docentes": "[{\"Id_docente\" : 16235, \"Nome_docente\" : \"Mariane Martins De Araujo Stefani\", \"Ch_teorica\" : 32, \"Ch_pratica\" : 0}]"
    },
    {
      "id_turma": 842171,
      "codigo_turma": "A",
      "ano": 2015,
      "periodo": 1,
      "id_curso_responsavel_oferta": null,
      "id_componente_curricular": 194616,
      "codigo_componente_curricular": "IPT0100",
      "nome_componente_curricular": "Tópicos Avançados Em Biotecnologia Iii",
      "nivel": "G",
      "tipo": 1,
      "tipo_turma": "Regular",
      "situacao_turma": "Consolidada",
      "horario": "6m45 (23/02/2015 - 04/07/2015)",
      "local": "Ca-D",
      "capacidade_aluno": 32,
      "total_matriculados": 25,
      "qtd_docentes": 2,
      "docentes": "[{\"Id_docente\" : 24517, \"Nome_docente\" : \"Ana Paula Junqueira Kipnis\", \"Ch_teorica\" : 16, \"Ch_pratica\" : 0}, {\"Id_docente\" : 23072, \"Nome_docente\" : \"Simone Goncalves Da Fonseca\", \"Ch_teorica\" : 16, \"Ch_pratica\" : 0}]"
    },
    {
      "id_turma": 842175,
      "codigo_turma": "A",
      "ano": 2015,
      "periodo": 1,
      "id_curso_responsavel_oferta": null,
      "id_componente_curricular": 187469,
      "codigo_componente_curricular": "EMA0553",
      "nome_componente_curricular": "Instrumento 3",
      "nivel": "G",
      "tipo": 1,
      "tipo_turma": "Regular",
      "situacao_turma": "Consolidada",
      "horario": "7m1",
      "local": "Emac",
      "capacidade_aluno": 1,
      "total_matriculados": 1,
      "qtd_docentes": 1,
      "docentes": "[{\"Id_docente\" : 21385, \"Nome_docente\" : \"Johnson Joanesburg Anchieta Machado\", \"Ch_teorica\" : 0, \"Ch_pratica\" : 16}]"
    },
    {
      "id_turma": 842176,
      "codigo_turma": "B",
      "ano": 2015,
      "periodo": 1,
      "id_curso_responsavel_oferta": null,
      "id_componente_curricular": 187469,
      "codigo_componente_curricular": "EMA0553",
      "nome_componente_curricular": "Instrumento 3",
      "nivel": "G",
      "tipo": 1,
      "tipo_turma": "Regular",
      "situacao_turma": "Consolidada",
      "horario": "7m1",
      "local": "Emac",
      "capacidade_aluno": 1,
      "total_matriculados": 1,
      "qtd_docentes": 1,
      "docentes": "[{\"Id_docente\" : 19139, \"Nome_docente\" : \"Sonia Marta Rodrigues Raymundo\", \"Ch_teorica\" : 0, \"Ch_pratica\" : 16}]"
    },
    {
      "id_turma": 842177,
      "codigo_turma": "C",
      "ano": 2015,
      "periodo": 1,
      "id_curso_responsavel_oferta": null,
      "id_componente_curricular": 187469,
      "codigo_componente_curricular": "EMA0553",
      "nome_componente_curricular": "Instrumento 3",
      "nivel": "G",
      "tipo": 1,
      "tipo_turma": "Regular",
      "situacao_turma": "Consolidada",
      "horario": "7m1",
      "local": "Emac",
      "capacidade_aluno": 1,
      "total_matriculados": 1,
      "qtd_docentes": 1,
      "docentes": "[{\"Id_docente\" : 23295, \"Nome_docente\" : \"Luis Carlos Vasconcelos Furtado\", \"Ch_teorica\" : 0, \"Ch_pratica\" : 16}]"
    },
    {
      "id_turma": 842178,
      "codigo_turma": "D",
      "ano": 2015,
      "periodo": 1,
      "id_curso_responsavel_oferta": null,
      "id_componente_curricular": 187469,
      "codigo_componente_curricular": "EMA0553",
      "nome_componente_curricular": "Instrumento 3",
      "nivel": "G",
      "tipo": 1,
      "tipo_turma": "Regular",
      "situacao_turma": "Consolidada",
      "horario": "7m1",
      "local": "Emac",
      "capacidade_aluno": 1,
      "total_matriculados": 2,
      "qtd_docentes": 1,
      "docentes": "[{\"Id_docente\" : 24104, \"Nome_docente\" : \"Fabiano Da Silva Chagas\", \"Ch_teorica\" : 0, \"Ch_pratica\" : 16}]"
    },
    {
      "id_turma": 842179,
      "codigo_turma": "E",
      "ano": 2015,
      "periodo": 1,
      "id_curso_responsavel_oferta": null,
      "id_componente_curricular": 187469,
      "codigo_componente_curricular": "EMA0553",
      "nome_componente_curricular": "Instrumento 3",
      "nivel": "G",
      "tipo": 1,
      "tipo_turma": "Regular",
      "situacao_turma": "Consolidada",
      "horario": "6m1",
      "local": "Emac",
      "capacidade_aluno": 1,
      "total_matriculados": 1,
      "qtd_docentes": 1,
      "docentes": "[{\"Id_docente\" : 24104, \"Nome_docente\" : \"Fabiano Da Silva Chagas\", \"Ch_teorica\" : 0, \"Ch_pratica\" : 16}]"
    },
    {
      "id_turma": 842180,
      "codigo_turma": "F",
      "ano": 2015,
      "periodo": 1,
      "id_curso_responsavel_oferta": null,
      "id_componente_curricular": 187469,
      "codigo_componente_curricular": "EMA0553",
      "nome_componente_curricular": "Instrumento 3",
      "nivel": "G",
      "tipo": 1,
      "tipo_turma": "Regular",
      "situacao_turma": "Consolidada",
      "horario": "7m1",
      "local": "Emac",
      "capacidade_aluno": 1,
      "total_matriculados": 1,
      "qtd_docentes": 1,
      "docentes": "[{\"Id_docente\" : 26884, \"Nome_docente\" : \"Marcos Botelho Lage\", \"Ch_teorica\" : 0, \"Ch_pratica\" : 16}]"
    },
    {
      "id_turma": 842181,
      "codigo_turma": "G",
      "ano": 2015,
      "periodo": 1,
      "id_curso_responsavel_oferta": null,
      "id_componente_curricular": 187469,
      "codigo_componente_curricular": "EMA0553",
      "nome_componente_curricular": "Instrumento 3",
      "nivel": "G",
      "tipo": 1,
      "tipo_turma": "Regular",
      "situacao_turma": "Consolidada",
      "horario": "5m1",
      "local": "Emac",
      "capacidade_aluno": 1,
      "total_matriculados": 1,
      "qtd_docentes": 1,
      "docentes": "[{\"Id_docente\" : 26884, \"Nome_docente\" : \"Marcos Botelho Lage\", \"Ch_teorica\" : 0, \"Ch_pratica\" : 16}]"
    },
    {
      "id_turma": 842182,
      "codigo_turma": "H",
      "ano": 2015,
      "periodo": 1,
      "id_curso_responsavel_oferta": null,
      "id_componente_curricular": 187469,
      "codigo_componente_curricular": "EMA0553",
      "nome_componente_curricular": "Instrumento 3",
      "nivel": "G",
      "tipo": 1,
      "tipo_turma": "Regular",
      "situacao_turma": "Consolidada",
      "horario": "7m1",
      "local": "Emac",
      "capacidade_aluno": 1,
      "total_matriculados": 2,
      "qtd_docentes": 1,
      "docentes": "[{\"Id_docente\" : 27076, \"Nome_docente\" : \"Luciano Ferreira Pontes\", \"Ch_teorica\" : 0, \"Ch_pratica\" : 16}]"
    },
    {
      "id_turma": 842184,
      "codigo_turma": "I",
      "ano": 2015,
      "periodo": 1,
      "id_curso_responsavel_oferta": null,
      "id_componente_curricular": 187469,
      "codigo_componente_curricular": "EMA0553",
      "nome_componente_curricular": "Instrumento 3",
      "nivel": "G",
      "tipo": 1,
      "tipo_turma": "Regular",
      "situacao_turma": "Consolidada",
      "horario": "7m2",
      "local": "Emac",
      "capacidade_aluno": 1,
      "total_matriculados": 1,
      "qtd_docentes": 1,
      "docentes": "[{\"Id_docente\" : 27076, \"Nome_docente\" : \"Luciano Ferreira Pontes\", \"Ch_teorica\" : 0, \"Ch_pratica\" : 16}]"
    },
    {
      "id_turma": 842185,
      "codigo_turma": "J",
      "ano": 2015,
      "periodo": 1,
      "id_curso_responsavel_oferta": null,
      "id_componente_curricular": 187469,
      "codigo_componente_curricular": "EMA0553",
      "nome_componente_curricular": "Instrumento 3",
      "nivel": "G",
      "tipo": 1,
      "tipo_turma": "Regular",
      "situacao_turma": "Consolidada",
      "horario": "7m1",
      "local": "Emac",
      "capacidade_aluno": 1,
      "total_matriculados": 1,
      "qtd_docentes": 1,
      "docentes": "[{\"Id_docente\" : 18352, \"Nome_docente\" : \"Werner Aguiar\", \"Ch_teorica\" : 0, \"Ch_pratica\" : 16}]"
    },
    {
      "id_turma": 842186,
      "codigo_turma": "A",
      "ano": 2015,
      "periodo": 1,
      "id_curso_responsavel_oferta": null,
      "id_componente_curricular": 181029,
      "codigo_componente_curricular": "IPT0002",
      "nome_componente_curricular": "Água E Sustentabilidade",
      "nivel": "G",
      "tipo": 1,
      "tipo_turma": "Regular",
      "situacao_turma": "Consolidada",
      "horario": "4m23",
      "local": "Ca-D",
      "capacidade_aluno": 30,
      "total_matriculados": 49,
      "qtd_docentes": 1,
      "docentes": "[{\"Id_docente\" : 24298, \"Nome_docente\" : \"Ionizete Garcia Da Silva\", \"Ch_teorica\" : 32, \"Ch_pratica\" : 0}]"
    },
    {
      "id_turma": 842187,
      "codigo_turma": "A",
      "ano": 2015,
      "periodo": 1,
      "id_curso_responsavel_oferta": null,
      "id_componente_curricular": 193208,
      "codigo_componente_curricular": "IPT0088",
      "nome_componente_curricular": "Reciclagem, Meio Ambiente E Sustentabilidade",
      "nivel": "G",
      "tipo": 1,
      "tipo_turma": "Regular",
      "situacao_turma": "Consolidada",
      "horario": "4m45",
      "local": "Ca-D",
      "capacidade_aluno": 30,
      "total_matriculados": 50,
      "qtd_docentes": 1,
      "docentes": "[{\"Id_docente\" : 24298, \"Nome_docente\" : \"Ionizete Garcia Da Silva\", \"Ch_teorica\" : 32, \"Ch_pratica\" : 0}]"
    },
    {
      "id_turma": 842188,
      "codigo_turma": "A",
      "ano": 2015,
      "periodo": 1,
      "id_curso_responsavel_oferta": null,
      "id_componente_curricular": 187470,
      "codigo_componente_curricular": "EMA0554",
      "nome_componente_curricular": "Instrumento 4",
      "nivel": "G",
      "tipo": 1,
      "tipo_turma": "Regular",
      "situacao_turma": "Aberta",
      "horario": "6m1",
      "local": "Emac",
      "capacidade_aluno": 1,
      "total_matriculados": 0,
      "qtd_docentes": 1,
      "docentes": "[{\"Id_docente\" : 26884, \"Nome_docente\" : \"Marcos Botelho Lage\", \"Ch_teorica\" : 0, \"Ch_pratica\" : 16}]"
    },
    {
      "id_turma": 842189,
      "codigo_turma": "A",
      "ano": 2015,
      "periodo": 1,
      "id_curso_responsavel_oferta": null,
      "id_componente_curricular": 182903,
      "codigo_componente_curricular": "IPT0020",
      "nome_componente_curricular": "Controle De Insetos Urbanos",
      "nivel": "G",
      "tipo": 1,
      "tipo_turma": "Regular",
      "situacao_turma": "Consolidada",
      "horario": "5t23",
      "local": "Ca-D",
      "capacidade_aluno": 30,
      "total_matriculados": 43,
      "qtd_docentes": 2,
      "docentes": "[{\"Id_docente\" : 24381, \"Nome_docente\" : \"Heloisa Helena Garcia Da Silva\", \"Ch_teorica\" : 16, \"Ch_pratica\" : 0}, {\"Id_docente\" : 24298, \"Nome_docente\" : \"Ionizete Garcia Da Silva\", \"Ch_teorica\" : 16, \"Ch_pratica\" : 0}]"
    },
    {
      "id_turma": 842190,
      "codigo_turma": "A",
      "ano": 2015,
      "periodo": 1,
      "id_curso_responsavel_oferta": null,
      "id_componente_curricular": 187471,
      "codigo_componente_curricular": "EMA0555",
      "nome_componente_curricular": "Instrumento 5",
      "nivel": "G",
      "tipo": 1,
      "tipo_turma": "Regular",
      "situacao_turma": "Consolidada",
      "horario": "7m1",
      "local": "Emac",
      "capacidade_aluno": 1,
      "total_matriculados": 2,
      "qtd_docentes": 1,
      "docentes": "[{\"Id_docente\" : 14814, \"Nome_docente\" : \"Consuelo Quireze Rosa\", \"Ch_teorica\" : 0, \"Ch_pratica\" : 16}]"
    },
    {
      "id_turma": 842191,
      "codigo_turma": "B",
      "ano": 2015,
      "periodo": 1,
      "id_curso_responsavel_oferta": null,
      "id_componente_curricular": 187471,
      "codigo_componente_curricular": "EMA0555",
      "nome_componente_curricular": "Instrumento 5",
      "nivel": "G",
      "tipo": 1,
      "tipo_turma": "Regular",
      "situacao_turma": "Consolidada",
      "horario": "7m1",
      "local": "Emac",
      "capacidade_aluno": 1,
      "total_matriculados": 1,
      "qtd_docentes": 1,
      "docentes": "[{\"Id_docente\" : 14705, \"Nome_docente\" : \"Maria Lucia Mascarenhas Roriz E Pina\", \"Ch_teorica\" : 0, \"Ch_pratica\" : 16}]"
    },
    {
      "id_turma": 842192,
      "codigo_turma": "C",
      "ano": 2015,
      "periodo": 1,
      "id_curso_responsavel_oferta": null,
      "id_componente_curricular": 187471,
      "codigo_componente_curricular": "EMA0555",
      "nome_componente_curricular": "Instrumento 5",
      "nivel": "G",
      "tipo": 1,
      "tipo_turma": "Regular",
      "situacao_turma": "Aberta",
      "horario": "7m2",
      "local": "Emac",
      "capacidade_aluno": 1,
      "total_matriculados": 1,
      "qtd_docentes": 1,
      "docentes": "[{\"Id_docente\" : 21385, \"Nome_docente\" : \"Johnson Joanesburg Anchieta Machado\", \"Ch_teorica\" : 0, \"Ch_pratica\" : 16}]"
    },
    {
      "id_turma": 842193,
      "codigo_turma": "A",
      "ano": 2015,
      "periodo": 1,
      "id_curso_responsavel_oferta": null,
      "id_componente_curricular": 189623,
      "codigo_componente_curricular": "IPT0050",
      "nome_componente_curricular": "Micoses Oportunísticas",
      "nivel": "G",
      "tipo": 1,
      "tipo_turma": "Regular",
      "situacao_turma": "Consolidada",
      "horario": "2m23",
      "local": "Ca-D",
      "capacidade_aluno": 30,
      "total_matriculados": 39,
      "qtd_docentes": 1,
      "docentes": "[{\"Id_docente\" : 23343, \"Nome_docente\" : \"Evandro Leao Ribeiro\", \"Ch_teorica\" : 32, \"Ch_pratica\" : 0}]"
    },
    {
      "id_turma": 842194,
      "codigo_turma": "D",
      "ano": 2015,
      "periodo": 1,
      "id_curso_responsavel_oferta": null,
      "id_componente_curricular": 187471,
      "codigo_componente_curricular": "EMA0555",
      "nome_componente_curricular": "Instrumento 5",
      "nivel": "G",
      "tipo": 1,
      "tipo_turma": "Regular",
      "situacao_turma": "Consolidada",
      "horario": "7m4",
      "local": "Emac",
      "capacidade_aluno": 1,
      "total_matriculados": 2,
      "qtd_docentes": 1,
      "docentes": "[{\"Id_docente\" : 26884, \"Nome_docente\" : \"Marcos Botelho Lage\", \"Ch_teorica\" : 0, \"Ch_pratica\" : 16}]"
    },
    {
      "id_turma": 842195,
      "codigo_turma": "E",
      "ano": 2015,
      "periodo": 1,
      "id_curso_responsavel_oferta": null,
      "id_componente_curricular": 187471,
      "codigo_componente_curricular": "EMA0555",
      "nome_componente_curricular": "Instrumento 5",
      "nivel": "G",
      "tipo": 1,
      "tipo_turma": "Regular",
      "situacao_turma": "Aberta",
      "horario": "7m1",
      "local": "Emac",
      "capacidade_aluno": 1,
      "total_matriculados": 1,
      "qtd_docentes": 1,
      "docentes": "[{\"Id_docente\" : 20041, \"Nome_docente\" : \"Antonio Marcos Souza Cardoso\", \"Ch_teorica\" : 0, \"Ch_pratica\" : 16}]"
    },
    {
      "id_turma": 842196,
      "codigo_turma": "F",
      "ano": 2015,
      "periodo": 1,
      "id_curso_responsavel_oferta": null,
      "id_componente_curricular": 187471,
      "codigo_componente_curricular": "EMA0555",
      "nome_componente_curricular": "Instrumento 5",
      "nivel": "G",
      "tipo": 1,
      "tipo_turma": "Regular",
      "situacao_turma": "Consolidada",
      "horario": "7m3",
      "local": "Emac",
      "capacidade_aluno": 1,
      "total_matriculados": 2,
      "qtd_docentes": 1,
      "docentes": "[{\"Id_docente\" : 27076, \"Nome_docente\" : \"Luciano Ferreira Pontes\", \"Ch_teorica\" : 0, \"Ch_pratica\" : 16}]"
    },
    {
      "id_turma": 842197,
      "codigo_turma": "G",
      "ano": 2015,
      "periodo": 1,
      "id_curso_responsavel_oferta": null,
      "id_componente_curricular": 187471,
      "codigo_componente_curricular": "EMA0555",
      "nome_componente_curricular": "Instrumento 5",
      "nivel": "G",
      "tipo": 1,
      "tipo_turma": "Regular",
      "situacao_turma": "Consolidada",
      "horario": "7m1",
      "local": "Emac",
      "capacidade_aluno": 1,
      "total_matriculados": 2,
      "qtd_docentes": 1,
      "docentes": "[{\"Id_docente\" : 22495, \"Nome_docente\" : \"David Edward Gardner\", \"Ch_teorica\" : 0, \"Ch_pratica\" : 16}]"
    },
    {
      "id_turma": 842198,
      "codigo_turma": "H",
      "ano": 2015,
      "periodo": 1,
      "id_curso_responsavel_oferta": null,
      "id_componente_curricular": 187471,
      "codigo_componente_curricular": "EMA0555",
      "nome_componente_curricular": "Instrumento 5",
      "nivel": "G",
      "tipo": 1,
      "tipo_turma": "Regular",
      "situacao_turma": "Aberta",
      "horario": "7m1",
      "local": "Emac",
      "capacidade_aluno": 1,
      "total_matriculados": 1,
      "qtd_docentes": 1,
      "docentes": "[{\"Id_docente\" : 23566, \"Nome_docente\" : \"Pedro Luiz Martelli\", \"Ch_teorica\" : 0, \"Ch_pratica\" : 16}]"
    },
    {
      "id_turma": 842199,
      "codigo_turma": "A",
      "ano": 2015,
      "periodo": 1,
      "id_curso_responsavel_oferta": null,
      "id_componente_curricular": 187472,
      "codigo_componente_curricular": "EMA0556",
      "nome_componente_curricular": "Instrumento 6",
      "nivel": "G",
      "tipo": 1,
      "tipo_turma": "Regular",
      "situacao_turma": "Aberta",
      "horario": "7m2",
      "local": "Emac",
      "capacidade_aluno": 1,
      "total_matriculados": 0,
      "qtd_docentes": 1,
      "docentes": "[{\"Id_docente\" : 23566, \"Nome_docente\" : \"Pedro Luiz Martelli\", \"Ch_teorica\" : 0, \"Ch_pratica\" : 16}]"
    },
    {
      "id_turma": 842200,
      "codigo_turma": "A",
      "ano": 2015,
      "periodo": 1,
      "id_curso_responsavel_oferta": null,
      "id_componente_curricular": 187473,
      "codigo_componente_curricular": "EMA0557",
      "nome_componente_curricular": "Instrumento 7",
      "nivel": "G",
      "tipo": 1,
      "tipo_turma": "Regular",
      "situacao_turma": "Consolidada",
      "horario": "7m5",
      "local": "Emac",
      "capacidade_aluno": 1,
      "total_matriculados": 1,
      "qtd_docentes": 1,
      "docentes": "[{\"Id_docente\" : 26884, \"Nome_docente\" : \"Marcos Botelho Lage\", \"Ch_teorica\" : 0, \"Ch_pratica\" : 16}]"
    },
    {
      "id_turma": 842201,
      "codigo_turma": "B",
      "ano": 2015,
      "periodo": 1,
      "id_curso_responsavel_oferta": null,
      "id_componente_curricular": 187473,
      "codigo_componente_curricular": "EMA0557",
      "nome_componente_curricular": "Instrumento 7",
      "nivel": "G",
      "tipo": 1,
      "tipo_turma": "Regular",
      "situacao_turma": "Consolidada",
      "horario": "7m6",
      "local": "Emac",
      "capacidade_aluno": 1,
      "total_matriculados": 1,
      "qtd_docentes": 1,
      "docentes": "[{\"Id_docente\" : 26884, \"Nome_docente\" : \"Marcos Botelho Lage\", \"Ch_teorica\" : 0, \"Ch_pratica\" : 16}]"
    },
    {
      "id_turma": 842202,
      "codigo_turma": "C",
      "ano": 2015,
      "periodo": 1,
      "id_curso_responsavel_oferta": null,
      "id_componente_curricular": 187473,
      "codigo_componente_curricular": "EMA0557",
      "nome_componente_curricular": "Instrumento 7",
      "nivel": "G",
      "tipo": 1,
      "tipo_turma": "Regular",
      "situacao_turma": "Consolidada",
      "horario": "7m4",
      "local": "Emac",
      "capacidade_aluno": 1,
      "total_matriculados": 1,
      "qtd_docentes": 1,
      "docentes": "[{\"Id_docente\" : 27076, \"Nome_docente\" : \"Luciano Ferreira Pontes\", \"Ch_teorica\" : 0, \"Ch_pratica\" : 16}]"
    },
    {
      "id_turma": 842203,
      "codigo_turma": "D",
      "ano": 2015,
      "periodo": 1,
      "id_curso_responsavel_oferta": null,
      "id_componente_curricular": 187473,
      "codigo_componente_curricular": "EMA0557",
      "nome_componente_curricular": "Instrumento 7",
      "nivel": "G",
      "tipo": 1,
      "tipo_turma": "Regular",
      "situacao_turma": "Consolidada",
      "horario": "7m3",
      "local": "Emac",
      "capacidade_aluno": 1,
      "total_matriculados": 1,
      "qtd_docentes": 1,
      "docentes": "[{\"Id_docente\" : 23566, \"Nome_docente\" : \"Pedro Luiz Martelli\", \"Ch_teorica\" : 0, \"Ch_pratica\" : 16}]"
    },
    {
      "id_turma": 842204,
      "codigo_turma": "A",
      "ano": 2015,
      "periodo": 1,
      "id_curso_responsavel_oferta": null,
      "id_componente_curricular": 187474,
      "codigo_componente_curricular": "EMA0558",
      "nome_componente_curricular": "Instrumento 8",
      "nivel": "G",
      "tipo": 1,
      "tipo_turma": "Regular",
      "situacao_turma": "Aberta",
      "horario": "7m2",
      "local": "Emac",
      "capacidade_aluno": 1,
      "total_matriculados": 1,
      "qtd_docentes": 1,
      "docentes": "[{\"Id_docente\" : 19139, \"Nome_docente\" : \"Sonia Marta Rodrigues Raymundo\", \"Ch_teorica\" : 0, \"Ch_pratica\" : 16}]"
    },
    {
      "id_turma": 842205,
      "codigo_turma": "B",
      "ano": 2015,
      "periodo": 1,
      "id_curso_responsavel_oferta": null,
      "id_componente_curricular": 187474,
      "codigo_componente_curricular": "EMA0558",
      "nome_componente_curricular": "Instrumento 8",
      "nivel": "G",
      "tipo": 1,
      "tipo_turma": "Regular",
      "situacao_turma": "Aberta",
      "horario": "7m5",
      "local": "Emac",
      "capacidade_aluno": 1,
      "total_matriculados": 0,
      "qtd_docentes": 1,
      "docentes": "[{\"Id_docente\" : 27076, \"Nome_docente\" : \"Luciano Ferreira Pontes\", \"Ch_teorica\" : 0, \"Ch_pratica\" : 16}]"
    },
    {
      "id_turma": 842206,
      "codigo_turma": "A",
      "ano": 2015,
      "periodo": 1,
      "id_curso_responsavel_oferta": null,
      "id_componente_curricular": 187468,
      "codigo_componente_curricular": "EMA0552",
      "nome_componente_curricular": "Instrumento 2",
      "nivel": "G",
      "tipo": 1,
      "tipo_turma": "Regular",
      "situacao_turma": "Consolidada",
      "horario": "7m2",
      "local": "Emac",
      "capacidade_aluno": 1,
      "total_matriculados": 2,
      "qtd_docentes": 1,
      "docentes": "[{\"Id_docente\" : 20041, \"Nome_docente\" : \"Antonio Marcos Souza Cardoso\", \"Ch_teorica\" : 0, \"Ch_pratica\" : 16}]"
    },
    {
      "id_turma": 842207,
      "codigo_turma": "K",
      "ano": 2015,
      "periodo": 1,
      "id_curso_responsavel_oferta": null,
      "id_componente_curricular": 187469,
      "codigo_componente_curricular": "EMA0553",
      "nome_componente_curricular": "Instrumento 3",
      "nivel": "G",
      "tipo": 1,
      "tipo_turma": "Regular",
      "situacao_turma": "Consolidada",
      "horario": "7m3",
      "local": "Emac",
      "capacidade_aluno": 1,
      "total_matriculados": 1,
      "qtd_docentes": 1,
      "docentes": "[{\"Id_docente\" : 19139, \"Nome_docente\" : \"Sonia Marta Rodrigues Raymundo\", \"Ch_teorica\" : 0, \"Ch_pratica\" : 16}]"
    },
    {
      "id_turma": 842209,
      "codigo_turma": "B",
      "ano": 2015,
      "periodo": 1,
      "id_curso_responsavel_oferta": null,
      "id_componente_curricular": 189427,
      "codigo_componente_curricular": "EMC0158",
      "nome_componente_curricular": "Metodologia Científica",
      "nivel": "G",
      "tipo": 1,
      "tipo_turma": "Regular",
      "situacao_turma": "Consolidada",
      "horario": "7m34",
      "local": "Sala 13 Bloco B",
      "capacidade_aluno": 51,
      "total_matriculados": 66,
      "qtd_docentes": 1,
      "docentes": "[{\"Id_docente\" : 16222, \"Nome_docente\" : \"Weber Martins\", \"Ch_teorica\" : 32, \"Ch_pratica\" : 0}]"
    },
    {
      "id_turma": 842212,
      "codigo_turma": "L",
      "ano": 2015,
      "periodo": 1,
      "id_curso_responsavel_oferta": null,
      "id_componente_curricular": 187469,
      "codigo_componente_curricular": "EMA0553",
      "nome_componente_curricular": "Instrumento 3",
      "nivel": "G",
      "tipo": 1,
      "tipo_turma": "Regular",
      "situacao_turma": "Aberta",
      "horario": "6m1",
      "local": "Emac",
      "capacidade_aluno": 1,
      "total_matriculados": 1,
      "qtd_docentes": 1,
      "docentes": "[{\"Id_docente\" : 23295, \"Nome_docente\" : \"Luis Carlos Vasconcelos Furtado\", \"Ch_teorica\" : 0, \"Ch_pratica\" : 16}]"
    },
    {
      "id_turma": 842213,
      "codigo_turma": "M",
      "ano": 2015,
      "periodo": 1,
      "id_curso_responsavel_oferta": null,
      "id_componente_curricular": 187469,
      "codigo_componente_curricular": "EMA0553",
      "nome_componente_curricular": "Instrumento 3",
      "nivel": "G",
      "tipo": 1,
      "tipo_turma": "Regular",
      "situacao_turma": "Consolidada",
      "horario": "7m1",
      "local": "Emac",
      "capacidade_aluno": 1,
      "total_matriculados": 1,
      "qtd_docentes": 1,
      "docentes": "[{\"Id_docente\" : 21871, \"Nome_docente\" : \"Fabio Fonseca De Oliveira\", \"Ch_teorica\" : 0, \"Ch_pratica\" : 16}]"
    },
    {
      "id_turma": 842214,
      "codigo_turma": "N",
      "ano": 2015,
      "periodo": 1,
      "id_curso_responsavel_oferta": null,
      "id_componente_curricular": 187469,
      "codigo_componente_curricular": "EMA0553",
      "nome_componente_curricular": "Instrumento 3",
      "nivel": "G",
      "tipo": 1,
      "tipo_turma": "Regular",
      "situacao_turma": "Consolidada",
      "horario": "6m1",
      "local": "Emac",
      "capacidade_aluno": 1,
      "total_matriculados": 1,
      "qtd_docentes": 1,
      "docentes": "[{\"Id_docente\" : 21871, \"Nome_docente\" : \"Fabio Fonseca De Oliveira\", \"Ch_teorica\" : 0, \"Ch_pratica\" : 16}]"
    },
    {
      "id_turma": 842215,
      "codigo_turma": "O",
      "ano": 2015,
      "periodo": 1,
      "id_curso_responsavel_oferta": null,
      "id_componente_curricular": 187469,
      "codigo_componente_curricular": "EMA0553",
      "nome_componente_curricular": "Instrumento 3",
      "nivel": "G",
      "tipo": 1,
      "tipo_turma": "Regular",
      "situacao_turma": "Consolidada",
      "horario": "7m2",
      "local": "Emac",
      "capacidade_aluno": 1,
      "total_matriculados": 1,
      "qtd_docentes": 1,
      "docentes": "[{\"Id_docente\" : 14705, \"Nome_docente\" : \"Maria Lucia Mascarenhas Roriz E Pina\", \"Ch_teorica\" : 0, \"Ch_pratica\" : 16}]"
    },
    {
      "id_turma": 842216,
      "codigo_turma": "P",
      "ano": 2015,
      "periodo": 1,
      "id_curso_responsavel_oferta": null,
      "id_componente_curricular": 187469,
      "codigo_componente_curricular": "EMA0553",
      "nome_componente_curricular": "Instrumento 3",
      "nivel": "G",
      "tipo": 1,
      "tipo_turma": "Regular",
      "situacao_turma": "Aberta",
      "horario": "7m3",
      "local": "Emac",
      "capacidade_aluno": 1,
      "total_matriculados": 0,
      "qtd_docentes": 1,
      "docentes": "[{\"Id_docente\" : 14705, \"Nome_docente\" : \"Maria Lucia Mascarenhas Roriz E Pina\", \"Ch_teorica\" : 0, \"Ch_pratica\" : 16}]"
    },
    {
      "id_turma": 842218,
      "codigo_turma": "R",
      "ano": 2015,
      "periodo": 1,
      "id_curso_responsavel_oferta": null,
      "id_componente_curricular": 187469,
      "codigo_componente_curricular": "EMA0553",
      "nome_componente_curricular": "Instrumento 3",
      "nivel": "G",
      "tipo": 1,
      "tipo_turma": "Regular",
      "situacao_turma": "Consolidada",
      "horario": "7m6",
      "local": "Emac",
      "capacidade_aluno": 1,
      "total_matriculados": 1,
      "qtd_docentes": 1,
      "docentes": "[{\"Id_docente\" : 27076, \"Nome_docente\" : \"Luciano Ferreira Pontes\", \"Ch_teorica\" : 0, \"Ch_pratica\" : 16}]"
    },
    {
      "id_turma": 842219,
      "codigo_turma": "S",
      "ano": 2015,
      "periodo": 1,
      "id_curso_responsavel_oferta": null,
      "id_componente_curricular": 187469,
      "codigo_componente_curricular": "EMA0553",
      "nome_componente_curricular": "Instrumento 3",
      "nivel": "G",
      "tipo": 1,
      "tipo_turma": "Regular",
      "situacao_turma": "Consolidada",
      "horario": "7v1",
      "local": "Emac",
      "capacidade_aluno": 1,
      "total_matriculados": 2,
      "qtd_docentes": 1,
      "docentes": "[{\"Id_docente\" : 27076, \"Nome_docente\" : \"Luciano Ferreira Pontes\", \"Ch_teorica\" : 0, \"Ch_pratica\" : 16}]"
    },
    {
      "id_turma": 842220,
      "codigo_turma": "T",
      "ano": 2015,
      "periodo": 1,
      "id_curso_responsavel_oferta": null,
      "id_componente_curricular": 187469,
      "codigo_componente_curricular": "EMA0553",
      "nome_componente_curricular": "Instrumento 3",
      "nivel": "G",
      "tipo": 1,
      "tipo_turma": "Regular",
      "situacao_turma": "Consolidada",
      "horario": "6m1",
      "local": "Emac",
      "capacidade_aluno": 1,
      "total_matriculados": 1,
      "qtd_docentes": 1,
      "docentes": "[{\"Id_docente\" : 22495, \"Nome_docente\" : \"David Edward Gardner\", \"Ch_teorica\" : 0, \"Ch_pratica\" : 16}]"
    },
    {
      "id_turma": 842221,
      "codigo_turma": "U",
      "ano": 2015,
      "periodo": 1,
      "id_curso_responsavel_oferta": null,
      "id_componente_curricular": 187469,
      "codigo_componente_curricular": "EMA0553",
      "nome_componente_curricular": "Instrumento 3",
      "nivel": "G",
      "tipo": 1,
      "tipo_turma": "Regular",
      "situacao_turma": "Aberta",
      "horario": "7m1",
      "local": "Emac",
      "capacidade_aluno": 1,
      "total_matriculados": 0,
      "qtd_docentes": 1,
      "docentes": "[{\"Id_docente\" : 17908, \"Nome_docente\" : \"Eduardo Meirinhos\", \"Ch_teorica\" : 0, \"Ch_pratica\" : 16}]"
    },
    {
      "id_turma": 842222,
      "codigo_turma": "B",
      "ano": 2015,
      "periodo": 1,
      "id_curso_responsavel_oferta": null,
      "id_componente_curricular": 187470,
      "codigo_componente_curricular": "EMA0554",
      "nome_componente_curricular": "Instrumento 4",
      "nivel": "G",
      "tipo": 1,
      "tipo_turma": "Regular",
      "situacao_turma": "Consolidada",
      "horario": "7m3",
      "local": "Emac",
      "capacidade_aluno": 1,
      "total_matriculados": 1,
      "qtd_docentes": 1,
      "docentes": "[{\"Id_docente\" : 21385, \"Nome_docente\" : \"Johnson Joanesburg Anchieta Machado\", \"Ch_teorica\" : 0, \"Ch_pratica\" : 16}]"
    },
    {
      "id_turma": 842223,
      "codigo_turma": "C",
      "ano": 2015,
      "periodo": 1,
      "id_curso_responsavel_oferta": null,
      "id_componente_curricular": 187470,
      "codigo_componente_curricular": "EMA0554",
      "nome_componente_curricular": "Instrumento 4",
      "nivel": "G",
      "tipo": 1,
      "tipo_turma": "Regular",
      "situacao_turma": "Aberta",
      "horario": "7m4",
      "local": "Emac",
      "capacidade_aluno": 1,
      "total_matriculados": 1,
      "qtd_docentes": 1,
      "docentes": "[{\"Id_docente\" : 23566, \"Nome_docente\" : \"Pedro Luiz Martelli\", \"Ch_teorica\" : 0, \"Ch_pratica\" : 16}]"
    },
    {
      "id_turma": 842224,
      "codigo_turma": "D",
      "ano": 2015,
      "periodo": 1,
      "id_curso_responsavel_oferta": null,
      "id_componente_curricular": 187470,
      "codigo_componente_curricular": "EMA0554",
      "nome_componente_curricular": "Instrumento 4",
      "nivel": "G",
      "tipo": 1,
      "tipo_turma": "Regular",
      "situacao_turma": "Consolidada",
      "horario": "2m4",
      "local": "Emac",
      "capacidade_aluno": 1,
      "total_matriculados": 1,
      "qtd_docentes": 1,
      "docentes": "[{\"Id_docente\" : 23007, \"Nome_docente\" : \"Helvis Costa\", \"Ch_teorica\" : 0, \"Ch_pratica\" : 16}]"
    },
    {
      "id_turma": 842225,
      "codigo_turma": "I",
      "ano": 2015,
      "periodo": 1,
      "id_curso_responsavel_oferta": null,
      "id_componente_curricular": 187471,
      "codigo_componente_curricular": "EMA0555",
      "nome_componente_curricular": "Instrumento 5",
      "nivel": "G",
      "tipo": 1,
      "tipo_turma": "Regular",
      "situacao_turma": "Consolidada",
      "horario": "7m2",
      "local": "Emac",
      "capacidade_aluno": 1,
      "total_matriculados": 1,
      "qtd_docentes": 1,
      "docentes": "[{\"Id_docente\" : 14814, \"Nome_docente\" : \"Consuelo Quireze Rosa\", \"Ch_teorica\" : 0, \"Ch_pratica\" : 16}]"
    },
    {
      "id_turma": 842226,
      "codigo_turma": "J",
      "ano": 2015,
      "periodo": 1,
      "id_curso_responsavel_oferta": null,
      "id_componente_curricular": 187471,
      "codigo_componente_curricular": "EMA0555",
      "nome_componente_curricular": "Instrumento 5",
      "nivel": "G",
      "tipo": 1,
      "tipo_turma": "Regular",
      "situacao_turma": "Consolidada",
      "horario": "5m1",
      "local": "Emac",
      "capacidade_aluno": 1,
      "total_matriculados": 1,
      "qtd_docentes": 1,
      "docentes": "[{\"Id_docente\" : 22495, \"Nome_docente\" : \"David Edward Gardner\", \"Ch_teorica\" : 0, \"Ch_pratica\" : 16}]"
    },
    {
      "id_turma": 842227,
      "codigo_turma": "A",
      "ano": 2015,
      "periodo": 1,
      "id_curso_responsavel_oferta": null,
      "id_componente_curricular": 187891,
      "codigo_componente_curricular": "EMC0101",
      "nome_componente_curricular": "Introdução À Engenharia De Computação",
      "nivel": "G",
      "tipo": 1,
      "tipo_turma": "Regular",
      "situacao_turma": "Consolidada",
      "horario": "2t6  2n1",
      "local": "Sala 13, Bloco B Ou Sala 2, Bloco H | Emc",
      "capacidade_aluno": 65,
      "total_matriculados": 76,
      "qtd_docentes": 1,
      "docentes": "[{\"Id_docente\" : 21005, \"Nome_docente\" : \"Adriano Cesar Santana\", \"Ch_teorica\" : 32, \"Ch_pratica\" : 0}]"
    },
    {
      "id_turma": 842228,
      "codigo_turma": "E",
      "ano": 2015,
      "periodo": 1,
      "id_curso_responsavel_oferta": null,
      "id_componente_curricular": 187473,
      "codigo_componente_curricular": "EMA0557",
      "nome_componente_curricular": "Instrumento 7",
      "nivel": "G",
      "tipo": 1,
      "tipo_turma": "Regular",
      "situacao_turma": "Consolidada",
      "horario": "7m4",
      "local": "Emac",
      "capacidade_aluno": 1,
      "total_matriculados": 1,
      "qtd_docentes": 1,
      "docentes": "[{\"Id_docente\" : 19139, \"Nome_docente\" : \"Sonia Marta Rodrigues Raymundo\", \"Ch_teorica\" : 0, \"Ch_pratica\" : 16}]"
    },
    {
      "id_turma": 842229,
      "codigo_turma": "B",
      "ano": 2015,
      "periodo": 1,
      "id_curso_responsavel_oferta": null,
      "id_componente_curricular": 186215,
      "codigo_componente_curricular": "EMC0085",
      "nome_componente_curricular": "Fundamentos De Lógica",
      "nivel": "G",
      "tipo": 1,
      "tipo_turma": "Regular",
      "situacao_turma": "Consolidada",
      "horario": "7m56",
      "local": "Sala 13, Bloco B",
      "capacidade_aluno": 55,
      "total_matriculados": 68,
      "qtd_docentes": 1,
      "docentes": "[{\"Id_docente\" : 16222, \"Nome_docente\" : \"Weber Martins\", \"Ch_teorica\" : 32, \"Ch_pratica\" : 0}]"
    },
    {
      "id_turma": 842230,
      "codigo_turma": "B",
      "ano": 2015,
      "periodo": 1,
      "id_curso_responsavel_oferta": null,
      "id_componente_curricular": 189607,
      "codigo_componente_curricular": "EMC0160",
      "nome_componente_curricular": "Métodos Matemáticos Lineares",
      "nivel": "G",
      "tipo": 1,
      "tipo_turma": "Regular",
      "situacao_turma": "Consolidada",
      "horario": "7m34  4n45",
      "local": "Sala 07 Bloco B",
      "capacidade_aluno": 52,
      "total_matriculados": 82,
      "qtd_docentes": 1,
      "docentes": "[{\"Id_docente\" : 21757, \"Nome_docente\" : \"Sandrerley Ramos Pires\", \"Ch_teorica\" : 64, \"Ch_pratica\" : 0}]"
    },
    {
      "id_turma": 842231,
      "codigo_turma": "A",
      "ano": 2015,
      "periodo": 1,
      "id_curso_responsavel_oferta": null,
      "id_componente_curricular": 193909,
      "codigo_componente_curricular": "EMC0214",
      "nome_componente_curricular": "Sistemas De Controle",
      "nivel": "G",
      "tipo": 1,
      "tipo_turma": "Regular",
      "situacao_turma": "Consolidada",
      "horario": "35n23",
      "local": "Sala 11 Bloco B",
      "capacidade_aluno": 40,
      "total_matriculados": 22,
      "qtd_docentes": 1,
      "docentes": "[{\"Id_docente\" : 18044, \"Nome_docente\" : \"Marco Antonio Assfalk De Oliveira\", \"Ch_teorica\" : 32, \"Ch_pratica\" : 0}]"
    },
    {
      "id_turma": 842235,
      "codigo_turma": "A",
      "ano": 2015,
      "periodo": 1,
      "id_curso_responsavel_oferta": null,
      "id_componente_curricular": 194404,
      "codigo_componente_curricular": "EMC0226",
      "nome_componente_curricular": "Teoria De Telecomunicações",
      "nivel": "G",
      "tipo": 1,
      "tipo_turma": "Regular",
      "situacao_turma": "Consolidada",
      "horario": "24n23",
      "local": "Sala 10 Bloco B",
      "capacidade_aluno": 40,
      "total_matriculados": 17,
      "qtd_docentes": 1,
      "docentes": "[{\"Id_docente\" : 21146, \"Nome_docente\" : \"Flavio Henrique Teles Vieira\", \"Ch_teorica\" : 32, \"Ch_pratica\" : 0}]"
    }
  ],
  "total_itens": 100907,
  "itens_por_pagina": 100,
  "pagina": 1,
  "total_paginas": 1010,
  "ordenar_por": "1",
  "ordem": "ASC"
}